SnapchatAdsWindsorApi/__init__.py
SnapchatAdsWindsorApi/client.py
SnapchatAdsWindsorApi/enums.py
test/__init__.py
test/tests.py
SnapchatAdsWindsorApi-1.0.6.dist-info/METADATA
SnapchatAdsWindsorApi-1.0.6.dist-info/WHEEL
SnapchatAdsWindsorApi-1.0.6.dist-info/top_level.txt
SnapchatAdsWindsorApi-1.0.6.dist-info/RECORD
